absTools/__init__.py
absTools/__main__.py
absTools-1.0.0.dev0.dist-info/METADATA
absTools-1.0.0.dev0.dist-info/WHEEL
absTools-1.0.0.dev0.dist-info/top_level.txt
absTools-1.0.0.dev0.dist-info/RECORD
