Metadata-Version: 2.1
Name: absTools
Version: 1.0.0.dev0
Summary: Abstract tools providing miscellaneous functionality for generic reuse
Home-page: https://github.com/IsotopeC/absTools
Author: Calvin Peters
Author-email: calvin.isotope@gmail.com
License: UNKNOWN
Keywords: absTools generic miscellaneous tools
Platform: UNKNOWN
Classifier: Programming Language :: Python :: 3
Classifier: Operating System :: OS Independent
Requires-Python: >3.8
Requires-Dist: numpy
Requires-Dist: pandas
